{
  "transactions": [
    {
      "id": "1746950759095",
      "date": "2025-02-01",
      "type": "expense",
      "category": "utilities",
      "paymentMethod": "cash",
      "amount": 600000,
      "memo": "월세",
      "createdAt": "2025-05-11T08:05:59.096Z"
    },
    {
      "id": "1746950819719",
      "date": "2025-02-01",
      "type": "expense",
      "category": "utilities",
      "paymentMethod": "cash",
      "amount": 9800,
      "memo": "수도세",
      "createdAt": "2025-05-11T08:06:59.719Z"
    },
    {
      "id": "1746950886499",
      "date": "2025-02-01",
      "type": "expense",
      "category": "utilities",
      "paymentMethod": "cash",
      "amount": 30500,
      "memo": "전기세",
      "createdAt": "2025-05-11T08:08:06.499Z"
    },
    {
      "id": "1746950914813",
      "date": "2025-02-01",
      "type": "expense",
      "category": "utilities",
      "paymentMethod": "cash",
      "amount": 70000,
      "memo": "관리비",
      "createdAt": "2025-05-11T08:08:34.813Z"
    },
    {
      "id": "1746951011899",
      "date": "2025-02-01",
      "type": "expense",
      "category": "utilities",
      "paymentMethod": "cash",
      "amount": 48000,
      "memo": "가스비",
      "createdAt": "2025-05-11T08:10:11.899Z"
    },
    {
      "id": "1746951051051",
      "date": "2025-02-01",
      "type": "expense",
      "category": "utilities",
      "paymentMethod": "cash",
      "amount": 64260,
      "memo": "KT 휴대폰",
      "createdAt": "2025-05-11T08:10:51.051Z"
    },
    {
      "id": "1746951076129",
      "date": "2025-02-01",
      "type": "expense",
      "category": "utilities",
      "paymentMethod": "cash",
      "amount": 8800,
      "memo": "인터넷 와이파이",
      "createdAt": "2025-05-11T08:11:16.129Z"
    },
    {
      "id": "1746951112734",
      "date": "2025-02-01",
      "type": "expense",
      "category": "etc",
      "paymentMethod": "card",
      "amount": 5500,
      "memo": "Netflix 기본 요금제 (광고형 스탠다드)",
      "createdAt": "2025-05-11T08:11:52.734Z"
    },
    {
      "id": "1746951146468",
      "date": "2025-02-01",
      "type": "expense",
      "category": "transportation",
      "paymentMethod": "card",
      "amount": 5000,
      "memo": "서울시 따릉이 1개월권",
      "createdAt": "2025-05-11T08:12:26.468Z"
    },
    {
      "id": "1746951196552",
      "date": "2025-02-01",
      "type": "expense",
      "category": "transportation",
      "paymentMethod": "card",
      "amount": 13100,
      "memo": "교통카드 비용",
      "createdAt": "2025-05-11T08:13:16.552Z"
    },
    {
      "id": "1746951220086",
      "date": "2025-02-01",
      "type": "income",
      "category": "salary",
      "paymentMethod": "",
      "amount": 750000,
      "memo": "학원 강습 알바",
      "createdAt": "2025-05-11T08:13:40.086Z"
    },
    {
      "id": "1746951244570",
      "date": "2025-02-01",
      "type": "income",
      "category": "allowance",
      "paymentMethod": "",
      "amount": 1000000,
      "memo": "부모님 용돈",
      "createdAt": "2025-05-11T08:14:04.570Z"
    },
    {
      "id": "1746951287238",
      "date": "2025-02-01",
      "type": "expense",
      "category": "food",
      "paymentMethod": "card",
      "amount": 42000,
      "memo": "식재료 배송",
      "createdAt": "2025-05-11T08:14:47.238Z"
    },
    {
      "id": "1746951319252",
      "date": "2025-02-02",
      "type": "expense",
      "category": "supplies",
      "paymentMethod": "card",
      "amount": 24300,
      "memo": "피죤, 샴푸",
      "createdAt": "2025-05-11T08:15:19.252Z"
    },
    {
      "id": "1746951371475",
      "date": "2025-02-02",
      "type": "expense",
      "category": "food",
      "paymentMethod": "card",
      "amount": 17500,
      "memo": "배달 음식",
      "createdAt": "2025-05-11T08:16:11.475Z"
    },
    {
      "id": "1746951412323",
      "date": "2025-02-04",
      "type": "expense",
      "category": "dessert",
      "paymentMethod": "card",
      "amount": 12600,
      "memo": "편의점",
      "createdAt": "2025-05-11T08:16:52.323Z"
    },
    {
      "id": "1746951438359",
      "date": "2025-02-05",
      "type": "expense",
      "category": "supplies",
      "paymentMethod": "card",
      "amount": 10800,
      "memo": "주방세제, 치약",
      "createdAt": "2025-05-11T08:17:18.359Z"
    },
    {
      "id": "1746951491210",
      "date": "2025-02-05",
      "type": "expense",
      "category": "food",
      "paymentMethod": "card",
      "amount": 8000,
      "memo": "은혜떡볶이",
      "createdAt": "2025-05-11T08:18:11.210Z"
    },
    {
      "id": "1746951534645",
      "date": "2025-02-07",
      "type": "expense",
      "category": "shopping",
      "paymentMethod": "card",
      "amount": 9000,
      "memo": "다이소",
      "createdAt": "2025-05-11T08:18:54.645Z"
    },
    {
      "id": "1746951597928",
      "date": "2025-02-08",
      "type": "expense",
      "category": "food",
      "paymentMethod": "card",
      "amount": 35000,
      "memo": "식재료 배송",
      "createdAt": "2025-05-11T08:19:57.928Z"
    },
    {
      "id": "1746951636368",
      "date": "2025-02-10",
      "type": "expense",
      "category": "leisure",
      "paymentMethod": "card",
      "amount": 24000,
      "memo": "전시회 관람 <불멸의 화가 반 고흐>",
      "createdAt": "2025-05-11T08:20:36.368Z"
    },
    {
      "id": "1746951661098",
      "date": "2025-02-11",
      "type": "expense",
      "category": "food",
      "paymentMethod": "card",
      "amount": 22300,
      "memo": "배달 음식",
      "createdAt": "2025-05-11T08:21:01.098Z"
    },
    {
      "id": "1746951702398",
      "date": "2025-02-13",
      "type": "expense",
      "category": "food",
      "paymentMethod": "card",
      "amount": 11500,
      "memo": "가츠시",
      "createdAt": "2025-05-11T08:21:42.398Z"
    },
    {
      "id": "1746951733332",
      "date": "2025-02-14",
      "type": "expense",
      "category": "shopping",
      "paymentMethod": "card",
      "amount": 68000,
      "memo": "에이블리",
      "createdAt": "2025-05-11T08:22:13.332Z"
    },
    {
      "id": "1746951757065",
      "date": "2025-02-14",
      "type": "expense",
      "category": "shopping",
      "paymentMethod": "card",
      "amount": 11000,
      "memo": "다이소",
      "createdAt": "2025-05-11T08:22:37.065Z"
    },
    {
      "id": "1746951776483",
      "date": "2025-02-14",
      "type": "expense",
      "category": "shopping",
      "paymentMethod": "card",
      "amount": 49000,
      "memo": "올리브영",
      "createdAt": "2025-05-11T08:22:56.483Z"
    },
    {
      "id": "1746951803434",
      "date": "2025-02-15",
      "type": "expense",
      "category": "food",
      "paymentMethod": "card",
      "amount": 30000,
      "memo": "식재료 배송",
      "createdAt": "2025-05-11T08:23:23.434Z"
    },
    {
      "id": "1746951866685",
      "date": "2025-02-16",
      "type": "expense",
      "category": "food",
      "paymentMethod": "card",
      "amount": 12000,
      "memo": "스시붐",
      "createdAt": "2025-05-11T08:24:26.685Z"
    },
    {
      "id": "1746951885521",
      "date": "2025-02-16",
      "type": "expense",
      "category": "leisure",
      "paymentMethod": "card",
      "amount": 14000,
      "memo": "영화 관람",
      "createdAt": "2025-05-11T08:24:45.521Z"
    },
    {
      "id": "1746951911067",
      "date": "2025-02-17",
      "type": "expense",
      "category": "dessert",
      "paymentMethod": "card",
      "amount": 6000,
      "memo": "편의점",
      "createdAt": "2025-05-11T08:25:11.067Z"
    },
    {
      "id": "1746951960789",
      "date": "2025-02-19",
      "type": "expense",
      "category": "food",
      "paymentMethod": "card",
      "amount": 8100,
      "memo": "맥도날드",
      "createdAt": "2025-05-11T08:26:00.789Z"
    },
    {
      "id": "1746951980039",
      "date": "2025-02-20",
      "type": "expense",
      "category": "dessert",
      "paymentMethod": "card",
      "amount": 12100,
      "memo": "스타벅스",
      "createdAt": "2025-05-11T08:26:20.039Z"
    },
    {
      "id": "1746952005408",
      "date": "2025-02-22",
      "type": "expense",
      "category": "food",
      "paymentMethod": "card",
      "amount": 35000,
      "memo": "식재료 배송",
      "createdAt": "2025-05-11T08:26:45.408Z"
    },
    {
      "id": "1746952111526",
      "date": "2025-02-22",
      "type": "expense",
      "category": "shopping",
      "paymentMethod": "card",
      "amount": 89200,
      "memo": "올리브영",
      "createdAt": "2025-05-11T08:28:31.526Z"
    },
    {
      "id": "1746952130377",
      "date": "2025-02-23",
      "type": "expense",
      "category": "shopping",
      "paymentMethod": "card",
      "amount": 125700,
      "memo": "무신사",
      "createdAt": "2025-05-11T08:28:50.377Z"
    },
    {
      "id": "1746952154127",
      "date": "2025-02-27",
      "type": "expense",
      "category": "shopping",
      "paymentMethod": "card",
      "amount": 66600,
      "memo": "헤라 쿠션",
      "createdAt": "2025-05-11T08:29:14.127Z"
    },
    {
      "id": "1746952202994",
      "date": "2025-02-28",
      "type": "expense",
      "category": "contributions",
      "paymentMethod": "card",
      "amount": 30000,
      "memo": "친구 생일선물",
      "createdAt": "2025-05-11T08:30:02.994Z"
    },
    {
      "id": "1746952222526",
      "date": "2025-02-28",
      "type": "expense",
      "category": "contributions",
      "paymentMethod": "card",
      "amount": 35000,
      "memo": "개강 전 동기 모임",
      "createdAt": "2025-05-11T08:30:22.526Z"
    },
    {
      "id": "1746504409360",
      "date": "2025-05-01",
      "type": "expense",
      "category": "utilities",
      "paymentMethod": "cash",
      "amount": 600000,
      "memo": "월세",
      "createdAt": "2025-05-06T04:06:49.360Z"
    },
    {
      "id": "1746504432056",
      "date": "2025-05-01",
      "type": "expense",
      "category": "utilities",
      "paymentMethod": "cash",
      "amount": 10000,
      "memo": "수도세",
      "createdAt": "2025-05-06T04:07:12.056Z"
    },
    {
      "id": "1746504450218",
      "date": "2025-05-01",
      "type": "expense",
      "category": "utilities",
      "paymentMethod": "cash",
      "amount": 30000,
      "memo": "전기세",
      "createdAt": "2025-05-06T04:07:30.218Z"
    },
    {
      "id": "1746504464590",
      "date": "2025-05-01",
      "type": "expense",
      "category": "utilities",
      "paymentMethod": "cash",
      "amount": 10000,
      "memo": "관리비",
      "createdAt": "2025-05-06T04:07:44.590Z"
    },
    {
      "id": "1746504478902",
      "date": "2025-05-01",
      "type": "expense",
      "category": "utilities",
      "paymentMethod": "cash",
      "amount": 20000,
      "memo": "가스비",
      "createdAt": "2025-05-06T04:07:58.902Z"
    },
    {
      "id": "1746504507019",
      "date": "2025-05-01",
      "type": "expense",
      "category": "utilities",
      "paymentMethod": "cash",
      "amount": 50000,
      "memo": "휴대폰 통신비",
      "createdAt": "2025-05-06T04:08:27.019Z"
    },
    {
      "id": "1746504528047",
      "date": "2025-05-01",
      "type": "expense",
      "category": "utilities",
      "paymentMethod": "cash",
      "amount": 5500,
      "memo": "넷플릭스 구독료",
      "createdAt": "2025-05-06T04:08:48.047Z"
    },
    {
      "id": "1746504549399",
      "date": "2025-05-01",
      "type": "expense",
      "category": "transportation",
      "paymentMethod": "cash",
      "amount": 5000,
      "memo": "서울시 따릉이 1개월권",
      "createdAt": "2025-05-06T04:09:09.399Z"
    },
    {
      "id": "1746504708077",
      "date": "2025-05-01",
      "type": "expense",
      "category": "utilities",
      "paymentMethod": "cash",
      "amount": 8800,
      "memo": "인터넷 와이파이",
      "createdAt": "2025-05-06T04:11:48.077Z"
    },
    {
      "id": "1746504728049",
      "date": "2025-05-01",
      "type": "income",
      "category": "salary",
      "paymentMethod": "",
      "amount": 830000,
      "memo": "학원 강습 알바",
      "createdAt": "2025-05-06T04:12:08.049Z"
    },
    {
      "id": "1746504740995",
      "date": "2025-05-01",
      "type": "income",
      "category": "allowance",
      "paymentMethod": "",
      "amount": 500000,
      "memo": "부모님 용돈",
      "createdAt": "2025-05-06T04:12:20.995Z"
    },
    {
      "id": "1746504755700",
      "date": "2025-05-01",
      "type": "income",
      "category": "scholarship",
      "paymentMethod": "",
      "amount": 300000,
      "memo": "부트캠프 지원금",
      "createdAt": "2025-05-06T04:12:35.700Z"
    },
    {
      "id": "1746510416497",
      "date": "2025-05-01",
      "type": "expense",
      "category": "utilities",
      "paymentMethod": "cash",
      "amount": 100,
      "memo": "멜론",
      "createdAt": "2025-05-06T05:46:56.497Z"
    },
    {
      "id": "1746510776274",
      "date": "2025-05-03",
      "type": "expense",
      "category": "shopping",
      "paymentMethod": "cash",
      "amount": 56870,
      "memo": "에이블리",
      "createdAt": "2025-05-06T05:52:56.274Z"
    },
    {
      "id": "1746510791743",
      "date": "2025-05-03",
      "type": "expense",
      "category": "shopping",
      "paymentMethod": "cash",
      "amount": 24900,
      "memo": "에이블리",
      "createdAt": "2025-05-06T05:53:11.743Z"
    },
    {
      "id": "1746510824261",
      "date": "2025-05-07",
      "type": "expense",
      "category": "shopping",
      "paymentMethod": "cash",
      "amount": 33040,
      "memo": "에이블리",
      "createdAt": "2025-05-06T05:53:44.261Z"
    },
    {
      "id": "1746510844431",
      "date": "2025-05-16",
      "type": "expense",
      "category": "shopping",
      "paymentMethod": "cash",
      "amount": 62640,
      "memo": "에이블리",
      "createdAt": "2025-05-06T05:54:04.431Z"
    },
    {
      "id": "1746510865678",
      "date": "2025-05-20",
      "type": "expense",
      "category": "shopping",
      "paymentMethod": "cash",
      "amount": 35990,
      "memo": "에이블리",
      "createdAt": "2025-05-06T05:54:25.678Z"
    },
    {
      "id": "1746510881940",
      "date": "2025-05-23",
      "type": "expense",
      "category": "dessert",
      "paymentMethod": "cash",
      "amount": 13000,
      "memo": "스타벅스",
      "createdAt": "2025-05-06T05:54:41.940Z"
    },
    {
      "id": "1746510926817",
      "date": "2025-05-04",
      "type": "expense",
      "category": "shopping",
      "paymentMethod": "cash",
      "amount": 96000,
      "memo": "헤어 디자인펌",
      "createdAt": "2025-05-06T05:55:26.817Z"
    },
    {
      "id": "1746511008268",
      "date": "2025-05-16",
      "type": "expense",
      "category": "shopping",
      "paymentMethod": "cash",
      "amount": 60000,
      "memo": "네일 젤",
      "createdAt": "2025-05-06T05:56:48.268Z"
    },
    {
      "id": "1746511036227",
      "date": "2025-05-03",
      "type": "expense",
      "category": "shopping",
      "paymentMethod": "cash",
      "amount": 58000,
      "memo": "블러셔(마가렛),립스틱(베어그레이프)",
      "createdAt": "2025-05-06T05:57:16.227Z"
    },
    {
      "id": "1746511057575",
      "date": "2025-05-07",
      "type": "expense",
      "category": "shopping",
      "paymentMethod": "cash",
      "amount": 26900,
      "memo": "토리든 세럼",
      "createdAt": "2025-05-06T05:57:37.575Z"
    },
    {
      "id": "1746511141428",
      "date": "2025-05-08",
      "type": "expense",
      "category": "shopping",
      "paymentMethod": "cash",
      "amount": 42200,
      "memo": "패브릭 쿠션 거울",
      "createdAt": "2025-05-06T05:59:01.428Z"
    },
    {
      "id": "1746511170627",
      "date": "2025-05-08",
      "type": "expense",
      "category": "shopping",
      "paymentMethod": "cash",
      "amount": 9400,
      "memo": "액자포스터",
      "createdAt": "2025-05-06T05:59:30.627Z"
    },
    {
      "id": "1746511233935",
      "date": "2025-05-11",
      "type": "expense",
      "category": "shopping",
      "paymentMethod": "cash",
      "amount": 99900,
      "memo": "차렵이불세트(피치샤베트)",
      "createdAt": "2025-05-06T06:00:33.935Z"
    },
    {
      "id": "1746511301102",
      "date": "2025-05-09",
      "type": "expense",
      "category": "shopping",
      "paymentMethod": "cash",
      "amount": 19900,
      "memo": "메탈하의걸이(10개)",
      "createdAt": "2025-05-06T06:01:41.102Z"
    },
    {
      "id": "1746511325416",
      "date": "2025-05-11",
      "type": "expense",
      "category": "shopping",
      "paymentMethod": "cash",
      "amount": 27000,
      "memo": "룸슈즈 1+1\n(레몬소다,아이보리핑크)",
      "createdAt": "2025-05-06T06:02:05.416Z"
    },
    {
      "id": "1746511363295",
      "date": "2025-05-12",
      "type": "expense",
      "category": "shopping",
      "paymentMethod": "cash",
      "amount": 50000,
      "memo": "다이소",
      "createdAt": "2025-05-06T06:02:43.295Z"
    },
    {
      "id": "1746511446063",
      "date": "2025-05-05",
      "type": "expense",
      "category": "shopping",
      "paymentMethod": "cash",
      "amount": 13850,
      "memo": "순수한면(중형+대형)",
      "createdAt": "2025-05-06T06:04:06.063Z"
    },
    {
      "id": "1746511463505",
      "date": "2025-05-26",
      "type": "expense",
      "category": "shopping",
      "paymentMethod": "cash",
      "amount": 47900,
      "memo": "크록스 바야플랫폼클로그",
      "createdAt": "2025-05-06T06:04:23.505Z"
    },
    {
      "id": "1746511479108",
      "date": "2025-05-07",
      "type": "expense",
      "category": "food",
      "paymentMethod": "cash",
      "amount": 13000,
      "memo": "유가네닭갈비",
      "createdAt": "2025-05-06T06:04:39.108Z"
    },
    {
      "id": "1746511494336",
      "date": "2025-05-08",
      "type": "expense",
      "category": "food",
      "paymentMethod": "cash",
      "amount": 11000,
      "memo": "육전국밥",
      "createdAt": "2025-05-06T06:04:54.336Z"
    },
    {
      "id": "1746511516525",
      "date": "2025-05-09",
      "type": "expense",
      "category": "food",
      "paymentMethod": "cash",
      "amount": 10500,
      "memo": "샤브로21",
      "createdAt": "2025-05-06T06:05:16.525Z"
    },
    {
      "id": "1746511530179",
      "date": "2025-05-12",
      "type": "expense",
      "category": "food",
      "paymentMethod": "cash",
      "amount": 11000,
      "memo": "서울뼈칼국수",
      "createdAt": "2025-05-06T06:05:30.179Z"
    },
    {
      "id": "1746511552295",
      "date": "2025-05-13",
      "type": "expense",
      "category": "food",
      "paymentMethod": "cash",
      "amount": 13000,
      "memo": "금하",
      "createdAt": "2025-05-06T06:05:52.295Z"
    },
    {
      "id": "1746511586255",
      "date": "2025-05-14",
      "type": "expense",
      "category": "food",
      "paymentMethod": "cash",
      "amount": 8000,
      "memo": "학식",
      "createdAt": "2025-05-06T06:06:26.255Z"
    },
    {
      "id": "1746511605443",
      "date": "2025-05-15",
      "type": "expense",
      "category": "food",
      "paymentMethod": "cash",
      "amount": 16500,
      "memo": "사토규카츠",
      "createdAt": "2025-05-06T06:06:45.443Z"
    },
    {
      "id": "1746511642009",
      "date": "2025-05-16",
      "type": "expense",
      "category": "food",
      "paymentMethod": "cash",
      "amount": 10000,
      "memo": "멘츠루",
      "createdAt": "2025-05-06T06:07:22.009Z"
    },
    {
      "id": "1746511656255",
      "date": "2025-05-19",
      "type": "expense",
      "category": "food",
      "paymentMethod": "cash",
      "amount": 11000,
      "memo": "소사면옥",
      "createdAt": "2025-05-06T06:07:36.255Z"
    },
    {
      "id": "1746511684778",
      "date": "2025-05-05",
      "type": "expense",
      "category": "food",
      "paymentMethod": "cash",
      "amount": 12960,
      "memo": "제주삼다수(2L*12개)",
      "createdAt": "2025-05-06T06:08:04.778Z"
    },
    {
      "id": "1746511712246",
      "date": "2025-05-05",
      "type": "expense",
      "category": "food",
      "paymentMethod": "cash",
      "amount": 15900,
      "memo": "엉클탁 (백미 5kg)",
      "createdAt": "2025-05-06T06:08:32.246Z"
    },
    {
      "id": "1746511734228",
      "date": "2025-05-05",
      "type": "expense",
      "category": "food",
      "paymentMethod": "cash",
      "amount": 4360,
      "memo": "짜요짜요(딸기*6개입*2)",
      "createdAt": "2025-05-06T06:08:54.228Z"
    },
    {
      "id": "1746511757369",
      "date": "2025-05-05",
      "type": "expense",
      "category": "food",
      "paymentMethod": "cash",
      "amount": 14820,
      "memo": "곰곰 치킨너겟(850g*2)",
      "createdAt": "2025-05-06T06:09:17.369Z"
    },
    {
      "id": "1746511776504",
      "date": "2025-05-05",
      "type": "expense",
      "category": "food",
      "paymentMethod": "cash",
      "amount": 10560,
      "memo": "곰곰 광천 도시락김 (5g*32)",
      "createdAt": "2025-05-06T06:09:36.504Z"
    },
    {
      "id": "1746511797227",
      "date": "2025-05-05",
      "type": "expense",
      "category": "food",
      "paymentMethod": "cash",
      "amount": 9480,
      "memo": "목계촌 특란(30구)",
      "createdAt": "2025-05-06T06:09:57.227Z"
    },
    {
      "id": "1746511808096",
      "date": "2025-05-05",
      "type": "expense",
      "category": "food",
      "paymentMethod": "cash",
      "amount": 13400,
      "memo": "비비고 썰은김치(1.2kg)",
      "createdAt": "2025-05-06T06:10:08.096Z"
    },
    {
      "id": "1746511841030",
      "date": "2025-05-24",
      "type": "expense",
      "category": "etc",
      "paymentMethod": "cash",
      "amount": 16020,
      "memo": "토익 ets 1000제 ",
      "createdAt": "2025-05-06T06:10:41.030Z"
    },
    {
      "id": "1746511859025",
      "date": "2025-05-02",
      "type": "expense",
      "category": "etc",
      "paymentMethod": "cash",
      "amount": 27000,
      "memo": "뇌를 자극하는 자바 (전공교재)",
      "createdAt": "2025-05-06T06:10:59.025Z"
    },
    {
      "id": "1746511882785",
      "date": "2025-05-15",
      "type": "expense",
      "category": "leisure",
      "paymentMethod": "cash",
      "amount": 10400,
      "memo": "야구 티켓팅 1루 내야석",
      "createdAt": "2025-05-06T06:11:22.785Z"
    }
  ],
  "budgets": [
    {
      "category": "food",
      "amount": 1000000,
      "month": "2025-04",
      "id": "f388"
    },
    {
      "category": "dessert",
      "amount": 100000,
      "month": "2025-04",
      "id": "f047"
    },
    {
      "category": "entertainment",
      "amount": 400000,
      "month": "2025-04",
      "id": "2ab8"
    },
    {
      "category": "shopping",
      "amount": 4000000,
      "month": "2025-04",
      "id": "b378"
    },
    {
      "category": "transportation",
      "amount": 0,
      "month": "2025-04",
      "id": "8aa8"
    },
    {
      "category": "utilities",
      "amount": 500000,
      "month": "2025-04",
      "id": "3e5b"
    },
    {
      "category": "health",
      "amount": 48088,
      "month": "2025-04",
      "id": "6ff9"
    },
    {
      "category": "leisure",
      "amount": 0,
      "month": "2025-04",
      "id": "14a8"
    },
    {
      "category": "travel",
      "amount": 0,
      "month": "2025-04",
      "id": "7e64"
    },
    {
      "category": "contributions",
      "amount": 0,
      "month": "2025-04",
      "id": "67cf"
    },
    {
      "category": "savings",
      "amount": 0,
      "month": "2025-04",
      "id": "9f7c"
    },
    {
      "category": "etc",
      "amount": 0,
      "month": "2025-04",
      "id": "6b4d"
    }
  ]
}
